nexus/__init__.py
nexus/cli/__init__.py
nexus/cli/api_client.py
nexus/cli/config.py
nexus/cli/jobs.py
nexus/cli/main.py
nexus/cli/setup.py
nexus/cli/shell_completion.py
nexus/cli/tunnel_manager.py
nexus/cli/utils.py
nexus/server/__init__.py
nexus/server/main.py
nexus/server/api/__init__.py
nexus/server/api/app.py
nexus/server/api/models.py
nexus/server/api/router.py
nexus/server/api/scheduler.py
nexus/server/core/__init__.py
nexus/server/core/config.py
nexus/server/core/context.py
nexus/server/core/db.py
nexus/server/core/exceptions.py
nexus/server/core/job.py
nexus/server/core/schemas.py
nexus/server/external/__init__.py
nexus/server/external/gpu.py
nexus/server/external/notifications.py
nexus/server/external/nullpointer.py
nexus/server/external/system.py
nexus/server/external/wandb_finder.py
nexus/server/installation/__init__.py
nexus/server/installation/setup.py
nexus/server/installation/systemd.py
nexus/server/utils/__init__.py
nexus/server/utils/format.py
nexus/server/utils/logger.py
nexusai-0.5.31.dist-info/METADATA
nexusai-0.5.31.dist-info/WHEEL
nexusai-0.5.31.dist-info/entry_points.txt
nexusai-0.5.31.dist-info/top_level.txt
nexusai-0.5.31.dist-info/RECORD
